main.py
youtube_face_enhancer-0.1.1.dist-info/licenses/LICENSE
youtube_face_enhancer-0.1.1.dist-info/METADATA
youtube_face_enhancer-0.1.1.dist-info/WHEEL
youtube_face_enhancer-0.1.1.dist-info/entry_points.txt
youtube_face_enhancer-0.1.1.dist-info/top_level.txt
youtube_face_enhancer-0.1.1.dist-info/RECORD
