Metadata-Version: 2.4
Name: youtube-face-enhancer
Version: 0.1.1
Summary: This tool enhances face images for YouTube thumbnails by removing the background, smoothing skin, boosting vibrance, sharpening, and adding a customizable glow.
License: MIT License Copyright (c) 2025 w3cj
Project-URL: Homepage, https://github.com/w3cj/youtube-face-enhancer
Project-URL: Repository, https://github.com/w3cj/youtube-face-enhancer
Requires-Python: >=3.11
License-File: LICENSE
Requires-Dist: numba>=0.61.2
Requires-Dist: rembg[cpu]>=2.0.67
Dynamic: license-file
